{"tweets": {"1471498715500146689": {"text": "\u2026yard then up into the tree. The screaming continues. My first thought is coyote. So I go into crocodile Dundee mode and grab one of the hunting knives I have stashed nearby and bolt outside. Only to realize it was Casanova being a dick to Big Boy and trying to chase him off\u2026", "geo": {"place_id": "07d9cac980087000"}, "possibly_sensitive": false, "created_at": "2021-12-16T15:13:27.000Z", "author_id": "373039972", "id": "1471498715500146689", "public_metrics": {"retweet_count": 0, "reply_count": 0, "like_count": 0, "quote_count": 0}, "lang": "en", "conversation_id": "1471498715500146689"}, "1428745317449551876": {"text": "Holy shnikes?! Hummingbirds do make sounds!!! I just watched a pair have a fight in my tree. I LOVE my mountain! I\u2019m so grateful for it. So many wildlife experiences on the ground and in the sky, I get to enjoy. Sans the coyotes. Those I could do without.  Heh.", "geo": {"place_id": "07d9cac980087000"}, "possibly_sensitive": false, "created_at": "2021-08-20T15:46:43.000Z", "author_id": "373039972", "id": "1428745317449551876", "public_metrics": {"retweet_count": 0, "reply_count": 0, "like_count": 0, "quote_count": 0}, "lang": "en", "conversation_id": "1428745317449551876"}, "1425615881480990721": {"text": "This Friday the 13th!!! First scrimmage of the season! The Snack Shack will be open!!! Come out to the #Safehouse and support your 2021 Coyotes \ud83d\udc3a\ud83d\udd10 https://t.co/qHSeLiXfho", "geo": {"place_id": "0fc300adc2555000"}, "possibly_sensitive": false, "created_at": "2021-08-12T00:31:27.000Z", "author_id": "3254139986", "id": "1425615881480990721", "public_metrics": {"retweet_count": 2, "reply_count": 1, "like_count": 11, "quote_count": 0}, "lang": "en", "attachments": {"media_keys": ["3_1425615878788313094"]}, "conversation_id": "1425615881480990721"}}, "users": {"373039972": {"description": "~I am anti-life,Beast of Judgement.I am the dark @ the end of e/thing.The end of universes,gods,worlds \u2026of e/thing.& what will U be then,Dreamlord? I am Hope.", "entities": {"url": {"urls": [{"start": 0, "end": 23, "url": "https://t.co/cYaViCTlsc", "expanded_url": "http://assholistic-ponderings.com", "display_url": "assholistic-ponderings.com"}]}}, "pinned_tweet_id": "811857769510731777", "protected": false, "id": "373039972", "name": "The Beast", "verified": false, "public_metrics": {"followers_count": 140, "following_count": 295, "tweet_count": 28696, "listed_count": 16}, "created_at": "2011-09-13T21:51:52.000Z", "profile_image_url": "https://pbs.twimg.com/profile_images/1064167856525369345/CJqiz5uC_normal.jpg", "username": "TheBeyst", "location": "Hell-A"}, "3254139986": {"description": "Calabasas High School Coyote Football Team \ud83d\udc3e Head Coach Cary Harris @caryharris07 2019 Marmonte League Champions #Safehouse", "entities": {"url": {"urls": [{"start": 0, "end": 23, "url": "https://t.co/MtQ90OKfWD", "expanded_url": "http://calabasasfootball.org", "display_url": "calabasasfootball.org"}]}, "description": {"hashtags": [{"start": 113, "end": 123, "tag": "Safehouse"}], "mentions": [{"start": 68, "end": 81, "username": "caryharris07"}]}}, "pinned_tweet_id": "1425307677681348609", "protected": false, "id": "3254139986", "name": "Calabasas High School Football", "verified": false, "public_metrics": {"followers_count": 5444, "following_count": 4024, "tweet_count": 17522, "listed_count": 29}, "created_at": "2015-06-24T01:21:40.000Z", "profile_image_url": "https://pbs.twimg.com/profile_images/1128658718755774464/ReweyD8x_normal.jpg", "username": "CalabasasFtball", "location": "Calabasas, CA"}}, "places": {"07d9cac980087000": {"name": "Top Of The World", "id": "07d9cac980087000", "full_name": "Top Of The World", "country": "United States", "place_type": "poi", "country_code": "US", "geo": {"type": "Feature", "bbox": [-118.54963816617517, 34.06469836684289, -118.54963816617517, 34.06469836684289], "properties": {}}}, "0fc300adc2555000": {"name": "Calabasas High Football Field", "id": "0fc300adc2555000", "full_name": "Calabasas High Football Field", "country": "United States", "place_type": "poi", "country_code": "US", "geo": {"type": "Feature", "bbox": [-118.62521131234983, 34.13808605628048, -118.62521131234983, 34.13808605628048], "properties": {}}}}, "grid_id": 3613}