{"tweets": {"546797825367896065": {"geo": {"place_id": "fbd6d2f5a4e4a15e", "coordinates": {"type": "Point", "coordinates": [-118.85524168, 34.11036885]}}, "lang": "en", "conversation_id": "546797825367896065", "id": "546797825367896065", "possibly_sensitive": false, "text": "Had a little visitor this morning. #Coyote #CanyonLife @ La Quonset de Malibu http://t.co/JqUPyFOFzF", "public_metrics": {"retweet_count": 0, "reply_count": 0, "like_count": 0, "quote_count": 0}, "author_id": "161174266", "created_at": "2014-12-21T22:42:15.000Z"}, "413223627048226816": {"text": "There's a loud pack of coyotes coyotying these fuckers sound like Charlie sheen on a pile of pornstars #outtacontrol", "geo": {"coordinates": {"type": "Point", "coordinates": [-118.86259053, 34.14097189]}, "place_id": "426b5a8bf757c0e5"}, "lang": "en", "possibly_sensitive": false, "public_metrics": {"retweet_count": 0, "reply_count": 0, "like_count": 1, "quote_count": 0}, "id": "413223627048226816", "created_at": "2013-12-18T08:26:04.000Z", "author_id": "347510350", "conversation_id": "413223627048226816"}, "413068700028137472": {"text": "#ThingsIDoInCalifornia hike with coyotes a stones throw away, with actual stones just in case! http://t.co/BFBAJncV7z", "geo": {"coordinates": {"type": "Point", "coordinates": [-118.87851796, 34.07868132]}, "place_id": "fbd6d2f5a4e4a15e"}, "lang": "en", "possibly_sensitive": false, "attachments": {"media_keys": ["3_413068699923263488"]}, "public_metrics": {"retweet_count": 0, "reply_count": 0, "like_count": 0, "quote_count": 0}, "id": "413068700028137472", "created_at": "2013-12-17T22:10:27.000Z", "author_id": "166028524", "conversation_id": "413068700028137472"}}, "users": {"161174266": {"location": "Malibu, Ca", "username": "courtney_ellis7", "created_at": "2010-06-30T04:56:45.000Z", "description": "Staff Resources Specialist at CSU Channel Islands. BA in Comm. w/Business minor. MA in Educational Leadership. Backstreet Boys fan. Daughter. Big sister.", "public_metrics": {"followers_count": 278, "following_count": 183, "tweet_count": 4956, "listed_count": 10}, "entities": {"url": {"urls": [{"start": 0, "end": 23, "url": "https://t.co/5hLnHnS54o", "expanded_url": "http://www.facebook.com/courtney.a.ellis", "display_url": "facebook.com/courtney.a.ell\u2026"}]}}, "name": "Courtney", "verified": false, "profile_image_url": "https://pbs.twimg.com/profile_images/819077311316140032/9t0NTYoj_normal.jpg", "id": "161174266", "protected": false}, "347510350": {"entities": {"url": {"urls": [{"start": 0, "end": 23, "url": "https://t.co/sG6gezHcDt", "expanded_url": "http://forbes.com", "display_url": "forbes.com"}]}}, "created_at": "2011-08-02T22:27:54.000Z", "protected": false, "username": "BillyLopsHigher", "description": "If Your Not The Lead Dogg, The View Never Changes- Big Bill Lopshire. Fashion, Fitness, Heavy Competition. Pimpin since Pimpins Been Pimpin playa!", "id": "347510350", "profile_image_url": "https://pbs.twimg.com/profile_images/759931127251349508/AXKccd9q_normal.jpg", "verified": false, "public_metrics": {"followers_count": 174, "following_count": 140, "tweet_count": 8859, "listed_count": 3}, "name": "William L.", "location": "westlake trillage."}, "166028524": {"entities": {"url": {"urls": [{"start": 0, "end": 23, "url": "https://t.co/9zFmf9Dc1y", "expanded_url": "http://abbeydufoe.com", "display_url": "abbeydufoe.com"}]}, "description": {"mentions": [{"start": 41, "end": 54, "username": "climatecosts"}, {"start": 55, "end": 66, "username": "Exxon_Knew"}]}}, "created_at": "2010-07-13T04:07:59.000Z", "protected": false, "username": "abbeydufoe", "description": "she/her \ud83c\udff3\ufe0f\u200d\ud83c\udf08 \u2022 \"watching the world burn\" @climatecosts/@Exxon_Knew \u2022 all I wanna do is go to emo nite \u2022 views obvi mine", "id": "166028524", "profile_image_url": "https://pbs.twimg.com/profile_images/1438294230984798215/NA61Ds0S_normal.jpg", "verified": false, "public_metrics": {"followers_count": 728, "following_count": 595, "tweet_count": 14073, "listed_count": 48}, "name": "Abbey Dufoe", "location": "the internet"}}, "places": {"fbd6d2f5a4e4a15e": {"country": "United States", "country_code": "US", "full_name": "California, USA", "geo": {"type": "Feature", "bbox": [-124.482003, 32.528832, -114.131212, 42.009519], "properties": {}}, "place_type": "admin", "name": "California", "id": "fbd6d2f5a4e4a15e"}, "426b5a8bf757c0e5": {"country": "United States", "country_code": "US", "full_name": "Triunfo Pass-Coastal, CA", "geo": {"type": "Feature", "bbox": [-119.068335, 33.992858, -118.849557, 34.162421], "properties": {}}, "place_type": "city", "name": "Triunfo Pass-Coastal", "id": "426b5a8bf757c0e5"}}, "grid_id": "3610"}