{"tweets": {"403921001605378048": {"conversation_id": "403921001605378048", "lang": "en", "author_id": "33148565", "geo": {"place_id": "fbd6d2f5a4e4a15e", "coordinates": {"type": "Point", "coordinates": [-116.96069062, 34.90726485]}}, "created_at": "2013-11-22T16:20:45.000Z", "id": "403921001605378048", "text": "Just saw a wild coyote crossing the road!! \ud83d\ude31\ud83d\udc3a @seth_turner3", "possibly_sensitive": false, "public_metrics": {"retweet_count": 0, "reply_count": 0, "like_count": 2, "quote_count": 0}}}, "users": {"33148565": {"protected": false, "id": "33148565", "description": "", "profile_image_url": "https://pbs.twimg.com/profile_images/1212316409084035072/89rP_TAA_normal.jpg", "public_metrics": {"followers_count": 423, "following_count": 510, "tweet_count": 5269, "listed_count": 4}, "created_at": "2009-04-19T06:23:37.000Z", "name": "Shardonnay Summerhays", "verified": false, "username": "sharsumm"}}, "places": {"fbd6d2f5a4e4a15e": {"id": "fbd6d2f5a4e4a15e", "name": "California", "place_type": "admin", "full_name": "California, USA", "country": "United States", "country_code": "US", "geo": {"type": "Feature", "bbox": [-124.482003, 32.528832, -114.131212, 42.009519], "properties": {}}}}, "grid_id": "3165"}