{"tweets": {"477758002657640448": {"conversation_id": "477758002657640448", "lang": "en", "author_id": "1054263872", "geo": {"place_id": "7e67fd2f1eeac401", "coordinates": {"type": "Point", "coordinates": [-120.61712479, 35.13892822]}}, "created_at": "2014-06-14T10:22:38.000Z", "id": "477758002657640448", "text": "Apparently it's feeding time for the pack of coyotes in my backyard right now \ud83d\ude12", "possibly_sensitive": false, "public_metrics": {"retweet_count": 0, "reply_count": 0, "like_count": 0, "quote_count": 0}}}, "users": {"1054263872": {"protected": false, "id": "1054263872", "description": "", "profile_image_url": "https://pbs.twimg.com/profile_images/888684662154907649/aPKYdKb__normal.jpg", "public_metrics": {"followers_count": 196, "following_count": 205, "tweet_count": 2374, "listed_count": 0}, "created_at": "2013-01-02T05:22:35.000Z", "name": "Callie Jay", "verified": false, "username": "CallieJNorton"}}, "places": {"7e67fd2f1eeac401": {"id": "7e67fd2f1eeac401", "name": "Pismo Beach", "place_type": "city", "full_name": "Pismo Beach, CA", "country": "United States", "country_code": "US", "geo": {"type": "Feature", "bbox": [-120.71479, 35.128494, -120.604645, 35.180956], "properties": {}}}}, "grid_id": "2968"}