{"tweets": {"881029655234572292": {"possibly_sensitive": false, "created_at": "2017-07-01T06:00:13.000Z", "id": "881029655234572292", "conversation_id": "881029655234572292", "lang": "en", "geo": {"coordinates": {"type": "Point", "coordinates": [-119.7600716, 36.92730625]}, "place_id": "fbd6d2f5a4e4a15e"}, "public_metrics": {"retweet_count": 0, "reply_count": 0, "like_count": 0, "quote_count": 0}, "text": "This guy was at Dragon Fly GC. The coyote being at Riverside GC, is\u2026 https://t.co/ZavM9PAsHJ", "author_id": "56615189"}, "571484559797186560": {"text": "\"Can we change the dogs name to coyote bait\"", "geo": {"place_id": "944c03c1d85ef480", "coordinates": {"type": "Point", "coordinates": [-119.72975358, 36.87251186]}}, "conversation_id": "571484559797186560", "public_metrics": {"retweet_count": 0, "reply_count": 0, "like_count": 1, "quote_count": 0}, "author_id": "1498517214", "created_at": "2015-02-28T01:38:31.000Z", "lang": "en", "id": "571484559797186560", "possibly_sensitive": false}, "479803428453883904": {"possibly_sensitive": false, "created_at": "2014-06-20T01:50:26.000Z", "id": "479803428453883904", "conversation_id": "479803428453883904", "lang": "en", "geo": {"coordinates": {"type": "Point", "coordinates": [-119.70742346, 36.86871827]}, "place_id": "fbd6d2f5a4e4a15e"}, "public_metrics": {"retweet_count": 0, "reply_count": 1, "like_count": 0, "quote_count": 0}, "text": "COYOTE TAILBACK NIGEL SIMMONS GETS FULL RIDE AT NEW MEXICO HIGHLANDS UNIVERSITY (PALM SPRINGS) -- SoCal Coyotes... http://t.co/VemwEoM3DV", "author_id": "331905616"}, "444713914358435840": {"created_at": "2014-03-15T05:57:14.000Z", "author_id": "783459979", "lang": "en", "public_metrics": {"retweet_count": 0, "reply_count": 0, "like_count": 0, "quote_count": 0}, "geo": {"place_id": "944c03c1d85ef480", "coordinates": {"type": "Point", "coordinates": [-119.73569423, 36.86743478]}}, "conversation_id": "444713914358435840", "text": "How have I never seen Coyote Ugly before this?!", "possibly_sensitive": false, "id": "444713914358435840"}, "423616493566562304": {"created_at": "2014-01-16T00:43:37.000Z", "author_id": "2279851993", "lang": "en", "public_metrics": {"retweet_count": 0, "reply_count": 0, "like_count": 0, "quote_count": 0}, "geo": {"place_id": "d374fb61a20fb74f", "coordinates": {"type": "Point", "coordinates": [-119.775395, 36.892263]}}, "conversation_id": "423616493566562304", "text": "Just saw a coyote \ud83d\ude01 on my run...yeeee! \ud83d\ude31\u263a\ufe0f (@ Lewis S Eaton Trail Woodward Park) http://t.co/mI4KrHE5Zo", "possibly_sensitive": false, "id": "423616493566562304"}, "385631780155314176": {"text": "I hear a coyote outside of my window. Woah.", "geo": {"place_id": "944c03c1d85ef480", "coordinates": {"type": "Point", "coordinates": [-119.77674905, 36.86682808]}}, "conversation_id": "385631780155314176", "public_metrics": {"retweet_count": 0, "reply_count": 0, "like_count": 0, "quote_count": 0}, "author_id": "1582133977", "created_at": "2013-10-03T05:05:55.000Z", "lang": "en", "id": "385631780155314176", "possibly_sensitive": false}, "366825099233468417": {"text": "Go to watch the meteor shower and hear far-off people yelling. Watch their cars leave and still hear the yelling. Realize it was coyotes.", "created_at": "2013-08-12T07:34:53.000Z", "id": "366825099233468417", "geo": {"place_id": "d3a7f19316bddcf6", "coordinates": {"type": "Point", "coordinates": [-119.7243408, 36.85779583]}}, "lang": "en", "public_metrics": {"retweet_count": 0, "reply_count": 0, "like_count": 0, "quote_count": 0}, "possibly_sensitive": false, "author_id": "311575826", "conversation_id": "366825099233468417"}, "286635487987367937": {"author_id": "293158558", "geo": {"place_id": "944c03c1d85ef480", "coordinates": {"type": "Point", "coordinates": [-119.77475493, 36.87221702]}}, "public_metrics": {"retweet_count": 3, "reply_count": 0, "like_count": 1, "quote_count": 0}, "id": "286635487987367937", "conversation_id": "286635487987367937", "created_at": "2013-01-03T00:50:00.000Z", "possibly_sensitive": false, "lang": "en", "text": "Coyotes might act big with their pack but are little bitches by themselves. Just like many kids in this town"}, "264973017040420864": {"public_metrics": {"retweet_count": 0, "reply_count": 0, "like_count": 0, "quote_count": 0}, "geo": {"place_id": "944c03c1d85ef480", "coordinates": {"type": "Point", "coordinates": [-119.77834758, 36.86833075]}}, "author_id": "405383633", "lang": "en", "possibly_sensitive": false, "id": "264973017040420864", "text": "If this cat doesn't stop meowing at the door I just might show him to the nearest coyote \ud83d\udc80\ud83d\ude21 #IHateCats", "created_at": "2012-11-04T06:11:04.000Z", "conversation_id": "264973017040420864"}}, "users": {"56615189": {"profile_image_url": "https://pbs.twimg.com/profile_images/637647976135917568/jpZelqME_normal.jpg", "verified": false, "username": "Mexi49", "name": "FLRamir", "public_metrics": {"followers_count": 40, "following_count": 84, "tweet_count": 2498, "listed_count": 3}, "description": "", "created_at": "2009-07-14T05:18:00.000Z", "protected": false, "id": "56615189"}, "1498517214": {"protected": false, "name": "sarah", "verified": false, "public_metrics": {"followers_count": 116, "following_count": 166, "tweet_count": 2786, "listed_count": 0}, "description": "be happy. be grateful.", "created_at": "2013-06-10T15:04:46.000Z", "username": "MommerSarah", "id": "1498517214", "profile_image_url": "https://pbs.twimg.com/profile_images/737107981196615680/a-CBG9PT_normal.jpg", "pinned_tweet_id": "711718683895160832"}, "331905616": {"profile_image_url": "https://pbs.twimg.com/profile_images/1469788535284764680/v2GSP-8I_normal.jpg", "verified": false, "username": "i_am_him5", "name": "Nigel Simmons", "public_metrics": {"followers_count": 1825, "following_count": 984, "tweet_count": 31284, "listed_count": 6}, "pinned_tweet_id": "1224075161508438018", "description": "Internet thugs be pie in real life... \u25b2 FATHER...PERSONAL TRAINER.... INVESTOR....", "created_at": "2011-07-08T22:24:01.000Z", "entities": {"url": {"urls": [{"start": 0, "end": 23, "url": "https://t.co/Zll72fSO3M", "expanded_url": "http://nigelsimmons.simpl.com", "display_url": "nigelsimmons.simpl.com"}]}}, "protected": false, "location": "California, USA", "id": "331905616"}, "783459979": {"description": "pediatric nurse & bravo fan. mom to Teddi the Little Bear (my dog).", "username": "hales_elisabeth", "id": "783459979", "verified": false, "protected": false, "name": "Haley", "profile_image_url": "https://pbs.twimg.com/profile_images/1117148856754376704/N6NvxLAN_normal.jpg", "public_metrics": {"followers_count": 375, "following_count": 604, "tweet_count": 25571, "listed_count": 12}, "created_at": "2012-08-27T00:21:10.000Z", "pinned_tweet_id": "1025972595760353280"}, "2279851993": {"description": "Love my family, traveling, running, adventure, outdoors, trying new things, music, laughing. #Lovelife #Californiagirl", "username": "SanterMsanter71", "id": "2279851993", "verified": false, "protected": false, "name": "Marjorie Santer", "profile_image_url": "https://pbs.twimg.com/profile_images/1049144586801537025/yJZwlQkC_normal.jpg", "public_metrics": {"followers_count": 12, "following_count": 12, "tweet_count": 557, "listed_count": 0}, "location": "Clovis, CA. ", "entities": {"description": {"hashtags": [{"start": 93, "end": 102, "tag": "Lovelife"}, {"start": 103, "end": 118, "tag": "Californiagirl"}]}}, "created_at": "2014-01-07T01:46:26.000Z"}, "1582133977": {"protected": false, "name": "Sarah Larkins", "verified": false, "public_metrics": {"followers_count": 100, "following_count": 0, "tweet_count": 981, "listed_count": 2}, "description": "I am \ud83c\uddf8\ufe0f\ud83c\uddea\ufe0f\ud83c\uddfd\ufe0f\ud83c\uddfe\ufe0f women. \ud83d\udc9e I wish torrid love. Attention \u26a0\ufe0f on my last tweet \u2b07\ufe0f \u2b07\ufe0f", "created_at": "2013-07-10T03:38:31.000Z", "username": "abbbbeyc", "id": "1582133977", "profile_image_url": "https://pbs.twimg.com/profile_images/823541824673509376/U4ub-rXT_normal.jpg", "pinned_tweet_id": "823539639571087360"}, "311575826": {"profile_image_url": "https://pbs.twimg.com/profile_images/1486230498657533953/p2Xjbyfu_normal.jpg", "location": "Los Angeles, CA", "name": "Hunter", "public_metrics": {"followers_count": 196, "following_count": 303, "tweet_count": 14751, "listed_count": 4}, "description": "lizard owner //// she/her", "protected": false, "created_at": "2011-06-05T17:47:29.000Z", "username": "HamHunter", "verified": false, "id": "311575826", "pinned_tweet_id": "944071495247994880"}, "293158558": {"verified": false, "location": "FRESNO, CA", "id": "293158558", "profile_image_url": "https://pbs.twimg.com/profile_images/1478147237737742339/zjA45Ob0_normal.jpg", "public_metrics": {"followers_count": 448, "following_count": 234, "tweet_count": 21312, "listed_count": 0}, "protected": false, "username": "SC_Spitta", "name": "Steven C", "created_at": "2011-05-04T21:22:04.000Z", "description": "thicker than a snicker"}, "405383633": {"name": "Jessica Potter", "id": "405383633", "entities": {"description": {"hashtags": [{"start": 0, "end": 10, "tag": "LoveJesus"}]}}, "profile_image_url": "https://pbs.twimg.com/profile_images/2778325480/00161d7089985d033933bb58398abbf6_normal.jpeg", "description": "#LoveJesus enough said", "verified": false, "protected": false, "created_at": "2011-11-05T07:23:10.000Z", "public_metrics": {"followers_count": 34, "following_count": 123, "tweet_count": 1129, "listed_count": 0}, "username": "jessiker21910"}}, "places": {"fbd6d2f5a4e4a15e": {"country_code": "US", "place_type": "admin", "country": "United States", "geo": {"type": "Feature", "bbox": [-124.482003, 32.528832, -114.131212, 42.009519], "properties": {}}, "name": "California", "id": "fbd6d2f5a4e4a15e", "full_name": "California, USA"}, "944c03c1d85ef480": {"geo": {"type": "Feature", "bbox": [-119.93251, 36.648905, -119.632419, 36.923179], "properties": {}}, "full_name": "Fresno, CA", "id": "944c03c1d85ef480", "country_code": "US", "country": "United States", "name": "Fresno", "place_type": "city"}, "d374fb61a20fb74f": {"country": "United States", "geo": {"type": "Feature", "bbox": [-120.00574, 35.002086, -114.039649, 42.002208], "properties": {}}, "place_type": "admin", "country_code": "US", "full_name": "Nevada, USA", "id": "d374fb61a20fb74f", "name": "Nevada"}, "d3a7f19316bddcf6": {"full_name": "Clovis, CA", "id": "d3a7f19316bddcf6", "country_code": "US", "geo": {"type": "Feature", "bbox": [-119.732263, 36.782957, -119.540115, 36.878641], "properties": {}}, "country": "United States", "name": "Clovis", "place_type": "city"}}, "grid_id": "2026"}